numpatterns/__init__.py
numpatterns/numpatt.py
numpatt_sequence-0.0.11.dist-info/LICENSE
numpatt_sequence-0.0.11.dist-info/METADATA
numpatt_sequence-0.0.11.dist-info/WHEEL
numpatt_sequence-0.0.11.dist-info/top_level.txt
numpatt_sequence-0.0.11.dist-info/RECORD
