Metadata-Version: 2.1
Name: numpatt-sequence
Version: 0.0.11
Summary: Number patterns in a sequence
Author: Dilith Achlan
Author-email: <dilith.achalan@outlook.com>
Keywords: python,number,patterns,number patterns,sequence,general term
Classifier: Development Status :: 1 - Planning
Classifier: Intended Audience :: Developers
Classifier: Programming Language :: Python :: 3
Classifier: Operating System :: Unix
Classifier: Operating System :: MacOS :: MacOS X
Classifier: Operating System :: Microsoft :: Windows
License-File: LICENSE
